sugar_yespower.cp36-win_amd64.pyd
sugar_yespower-1.0.1.dist-info/METADATA
sugar_yespower-1.0.1.dist-info/WHEEL
sugar_yespower-1.0.1.dist-info/top_level.txt
sugar_yespower-1.0.1.dist-info/RECORD
