Metadata-Version: 2.1
Name: sugar-yespower
Version: 1.0.1
Summary: Bindings for yespower-1.0 proof of work used by sugarchain
Home-page: https://github.com/sugarchain-dev/sugar_yespower_python3
Author: y-chan
Author-email: yuto_tetuota@yahoo.co.jp
License: UNKNOWN
Platform: UNKNOWN
